shipyard_microsoft_power_bi/__init__.py
shipyard_microsoft_power_bi/cli/__init__.py
shipyard_microsoft_power_bi/cli/authtest.py
shipyard_microsoft_power_bi/cli/trigger_sync.py
shipyard_microsoft_power_bi/microsoft_power_bi.py
shipyard_microsoft_power_bi/microsoft_power_bi_utils.py
shipyard_microsoft_power_bi-0.1.2.dist-info/METADATA
shipyard_microsoft_power_bi-0.1.2.dist-info/WHEEL
shipyard_microsoft_power_bi-0.1.2.dist-info/RECORD
