Metadata-Version: 2.1
Name: shipyard-microsoft-power-bi
Version: 0.1.2
Summary: 
Author: johnathan-rodriguez
Author-email: johnathan.rodriguez@shipyardapp.com
Requires-Python: >=3.9,<4.0
Classifier: Programming Language :: Python :: 3
Classifier: Programming Language :: Python :: 3.9
Classifier: Programming Language :: Python :: 3.10
Classifier: Programming Language :: Python :: 3.11
Requires-Dist: msal (>=1.26.0,<2.0.0)
Requires-Dist: shipyard-templates (>=0.9.0,<0.10.0)
